[
  {
    "id": "mercury",
    "name": "Mercury",
    "subtitle": "The Swift Planet",
    "distanceFromSun": "57.9 million km",
    "mass": "3.30 × 10^23 kg",
    "radius": "2,440 km",
    "temperature": "-180 to 430°C",
    "moons": 0,
    "orbitalPeriod": "88 days",
    "category": "Terrestrial",
    "color": "#9CA3AF",
    "orbitRadius": 10,
    "orbitSpeed": 4.15,
    "size": 0.4,
    "description": "Mercury is the smallest planet in our solar system and closest to the Sun. It has a heavily cratered surface resembling our Moon. Despite being nearest to the Sun, it is not the hottest planet — that title belongs to Venus. Mercury has virtually no atmosphere to retain heat, causing extreme temperature swings between day and night."
  },
  {
    "id": "venus",
    "name": "Venus",
    "subtitle": "The Evening Star",
    "distanceFromSun": "108.2 million km",
    "mass": "4.87 × 10^24 kg",
    "radius": "6,052 km",
    "temperature": "462°C",
    "moons": 0,
    "orbitalPeriod": "225 days",
    "category": "Terrestrial",
    "color": "#E5C07B",
    "orbitRadius": 15,
    "orbitSpeed": 1.62,
    "size": 0.95,
    "description": "Venus is the second planet from the Sun and the hottest planet in our solar system. Its thick, toxic atmosphere traps heat in a runaway greenhouse effect. Venus rotates in the opposite direction to most planets and is often called Earth's 'sister planet' due to their similar size and mass."
  },
  {
    "id": "earth",
    "name": "Earth",
    "subtitle": "The Blue Planet",
    "distanceFromSun": "149.6 million km",
    "mass": "5.97 × 10^24 kg",
    "radius": "6,371 km",
    "temperature": "15°C",
    "moons": 1,
    "orbitalPeriod": "365.25 days",
    "category": "Terrestrial",
    "color": "#3B82F6",
    "orbitRadius": 20,
    "orbitSpeed": 1.0,
    "size": 1.0,
    "description": "Earth is the third planet from the Sun and the only known world to harbor life. About 71% of its surface is covered in water. Its atmosphere protects life from harmful solar radiation. Earth's magnetic field shields the planet from the solar wind."
  },
  {
    "id": "mars",
    "name": "Mars",
    "subtitle": "The Red Planet",
    "distanceFromSun": "227.9 million km",
    "mass": "6.42 × 10^23 kg",
    "radius": "3,390 km",
    "temperature": "-65°C",
    "moons": 2,
    "orbitalPeriod": "687 days",
    "category": "Terrestrial",
    "color": "#EF4444",
    "orbitRadius": 25,
    "orbitSpeed": 0.53,
    "size": 0.53,
    "description": "Mars is the fourth planet from the Sun with a distinctive reddish appearance due to iron oxide on its surface. It has the tallest mountain (Olympus Mons) and the longest canyon (Valles Marineris) in the solar system. Mars has been a prime target for exploration in the search for past microbial life."
  },
  {
    "id": "jupiter",
    "name": "Jupiter",
    "subtitle": "The Giant Planet",
    "distanceFromSun": "778.5 million km",
    "mass": "1.90 × 10^27 kg",
    "radius": "69,911 km",
    "temperature": "-110°C",
    "moons": 95,
    "orbitalPeriod": "11.86 years",
    "category": "Gas Giant",
    "color": "#D97706",
    "orbitRadius": 35,
    "orbitSpeed": 0.08,
    "size": 2.5,
    "description": "Jupiter is the largest planet in our solar system, a gas giant with a mass more than twice that of all other planets combined. Its Great Red Spot is a storm larger than Earth that has been raging for centuries. Jupiter has a faint ring system and at least 95 known moons."
  },
  {
    "id": "saturn",
    "name": "Saturn",
    "subtitle": "The Ringed Planet",
    "distanceFromSun": "1.43 billion km",
    "mass": "5.68 × 10^26 kg",
    "radius": "58,232 km",
    "temperature": "-140°C",
    "moons": 146,
    "orbitalPeriod": "29.46 years",
    "category": "Gas Giant",
    "color": "#D4A574",
    "orbitRadius": 45,
    "orbitSpeed": 0.03,
    "size": 2.0,
    "description": "Saturn is the sixth planet from the Sun, best known for its spectacular ring system made of ice and rock particles. It is the second-largest planet and has the lowest density of any planet — it would float in water. Saturn's moon Titan has a thick atmosphere and liquid methane lakes."
  },
  {
    "id": "uranus",
    "name": "Uranus",
    "subtitle": "The Ice Giant",
    "distanceFromSun": "2.87 billion km",
    "mass": "8.68 × 10^25 kg",
    "radius": "25,362 km",
    "temperature": "-195°C",
    "moons": 27,
    "orbitalPeriod": "84 years",
    "category": "Ice Giant",
    "color": "#67E8F9",
    "orbitRadius": 55,
    "orbitSpeed": 0.01,
    "size": 1.5,
    "description": "Uranus is the seventh planet from the Sun, an ice giant with a blue-green color from methane in its atmosphere. It rotates on its side with an axial tilt of 98 degrees, likely caused by a massive ancient collision. Uranus has faint rings and a fleet of 27 known moons."
  },
  {
    "id": "neptune",
    "name": "Neptune",
    "subtitle": "The Windy Planet",
    "distanceFromSun": "4.50 billion km",
    "mass": "1.02 × 10^26 kg",
    "radius": "24,622 km",
    "temperature": "-200°C",
    "moons": 16,
    "orbitalPeriod": "164.8 years",
    "category": "Ice Giant",
    "color": "#2563EB",
    "orbitRadius": 65,
    "orbitSpeed": 0.006,
    "size": 1.4,
    "description": "Neptune is the eighth and farthest planet from the Sun, a dark, cold ice giant with the strongest winds in the solar system reaching up to 2,100 km/h. Its vivid blue color comes from methane in its atmosphere. Neptune was the first planet located through mathematical prediction rather than observation."
  }
]
